Workbook

Sheet Read Me
A1: Global Investment Decision Book
A2: Week to 2026-10-09 · Source: Interactive Brokers weekly closes via global-investment-research
A4: How to use
A5: 1. Enter your portfolio value on the Policy tab (yellow cell). Every Amount recalculates.
A6: 2. Policy tab: blue numbers are editable limits; all sizes and limit prices are formulas that use them.
A7: 3. Decisions tab: work the Accumulate rows first; pass the 5-question checklist before acting.
A8: 4. SG Income tab: limit-order prices for 6%, 7% and 8% trailing yield; change the band on Policy.
A9: 5. Decision Log tab: one row per decision (row 2 is a format example, delete it). Review monthly.
A11: Colour legend
A12: Blue text = input or engine output pasted as value · Black = formula · Green = link to another tab · Yellow fill = enter your own value
A14: Limits
A15: Mechanical price-trend, momentum and yield rules only: no valuation, fundamentals, costs or taxes. Not personalised advice.
A16: Full rules: docs/HANDBOOK.md in the repository.

Sheet Policy
A1: Setting | B1: Value | C1: Meaning
A2: Portfolio value (your base currency) | B2: 1000000 | C2: Enter your own figure
A3: Risk budget this week | B3: 1 | C3: Deploy 100% of the normal risk budget (Volatility calm).
A4: Risk per position | B4: 0.005 | C4: Loss if the exit level is hit, as share of portfolio
A5: Single stock cap | B5: 0.08 | C5: Maximum weight per company
A6: ETF / fund cap | B6: 0.2 | C6: Maximum weight per broad fund
A7: Exit buffer below 40-week average | B7: 0.03 | C7: Exit level = 40w average × (1 − buffer)
A8: Income band low | B8: 0.06 | C8: Singapore income target: lower bound
A9: Income band high | B9: 0.08 | C9: Singapore income target: upper bound
A10: Options sleeve cap | B10: 0.05 | C10: Total option premium at risk, share of portfolio
A11: Options per-trade risk | B11: 0.01 | C11: Premium at risk per option trade
A13: Portfolio tilts this week
A14: Keep bond duration short; avoid adding long Treasuries | C14: Because: Long yields rising (bond prices down-trend)
A15: Hedge or underweight non-USD assets for a USD-based portfolio; strong dollar is a headwind for HK/EM | C15: Because: Dollar strengthening
A16: Keep energy exposure (oil up-trend supports XLE/SHEL/XOM) | C16: Because: Oil in up-trend
A17: Do not add gold until it reclaims its 40-week average | C17: Because: Gold in down-trend
A18: Favour quality and defensives over consumer cyclicals | C18: Because: Defensives leading cyclicals
A19: Underweight China A-shares; wait for relative strength to turn | C19: Because: US outperforming China A-shares
A20: Keep Hong Kong at or below benchmark weight | C20: Because: US outperforming Hong Kong

Sheet Decisions
A1: Symbol | B1: Name | C1: Market | D1: Sector | E1: Type | F1: Decision | G1: Why | H1: Last | I1: Buy zone low | J1: Buy zone high | K1: 40w average | L1: Exit level | M1: Revisit above | N1: Distance to exit | O1: Max weight | P1: Amount | Q1: 3m return | R1: 1y return | S1: Momentum
A2: XLE | B2: Energy Select Sector ETF | C2: US | D2: Energy | E2: Fund | F2: Accumulate | G2: Up-trend with risk-adjusted momentum >= 0.5. | H2: 65.08 | I2: 62.918 | J2: 65.08 | K2: 57.312195 | L2: =IF(K2="","",K2*(1-Policy!$B$7)) -> 55.592829 | N2: =IF(L2="","",H2/L2-1) -> 0.17065458 | O2: =IF(AND(F2="Accumulate",N2<>"",N2>0),MIN(Policy!$B$4/N2,IF(E2="Stock",Policy!$B$5,Policy!$B$6)),"") -> 0.029298951 | P2: =IF(O2="","",O2*Policy!$B$3*Policy!$B$2) -> 29298.951 | Q2: 0.1815541 | R2: 0.51384043 | S2: 1.5113705
A3: SHEL | B3: Shell | C3: UK | D3: Energy | E3: Stock | F3: Accumulate | G3: Up-trend with risk-adjusted momentum >= 0.5. | H3: 37.954 | I3: 34.869 | J3: 37.954 | K3: 31.977512 | L3: =IF(K3="","",K3*(1-Policy!$B$7)) -> 31.018187 | N3: =IF(L3="","",H3/L3-1) -> 0.22360473 | O3: =IF(AND(F3="Accumulate",N3<>"",N3>0),MIN(Policy!$B$4/N3,IF(E3="Stock",Policy!$B$5,Policy!$B$6)),"") -> 0.022360887 | P3: =IF(O3="","",O3*Policy!$B$3*Policy!$B$2) -> 22360.887 | Q3: 0.24832259 | R3: 0.40967167 | S3: 1.412913
A4: XOM | B4: Exxon Mobil | C4: US | D4: Energy | E4: Stock | F4: Accumulate | G4: Up-trend with risk-adjusted momentum >= 0.5. | H4: 168.94 | I4: 161.75 | J4: 168.94 | K4: 150.66463 | L4: =IF(K4="","",K4*(1-Policy!$B$7)) -> 146.1447 | N4: =IF(L4="","",H4/L4-1) -> 0.15597764 | O4: =IF(AND(F4="Accumulate",N4<>"",N4>0),MIN(Policy!$B$4/N4,IF(E4="Stock",Policy!$B$5,Policy!$B$6)),"") -> 0.032055876 | P4: =IF(O4="","",O4*Policy!$B$3*Policy!$B$2) -> 32055.876 | Q4: 0.21644585 | R4: 0.5051675 | S4: 1.3868797
A5: CPER | B5: US Copper Index Fund | C5: Cross-asset | D5: Copper | E5: Fund | F5: Accumulate | G5: Up-trend with risk-adjusted momentum >= 0.5. | H5: 40.31 | I5: 39.937 | J5: 40.31 | K5: 37.568537 | L5: =IF(K5="","",K5*(1-Policy!$B$7)) -> 36.44148 | N5: =IF(L5="","",H5/L5-1) -> 0.10615703 | O5: =IF(AND(F5="Accumulate",N5<>"",N5>0),MIN(Policy!$B$4/N5,IF(E5="Stock",Policy!$B$5,Policy!$B$6)),"") -> 0.047100034 | P5: =IF(O5="","",O5*Policy!$B$3*Policy!$B$2) -> 47100.034 | Q5: 0.061068702 | R5: 0.33168153 | S5: 1.0388713
A6: XLK | B6: Technology Select Sector ETF | C6: US | D6: Technology | E6: Fund | F6: Accumulate | G6: Up-trend with risk-adjusted momentum >= 0.5. | H6: 198.78 | I6: 190.639 | J6: 198.78 | K6: 166.83268 | L6: =IF(K6="","",K6*(1-Policy!$B$7)) -> 161.8277 | N6: =IF(L6="","",H6/L6-1) -> 0.22834346 | O6: =IF(AND(F6="Accumulate",N6<>"",N6>0),MIN(Policy!$B$4/N6,IF(E6="Stock",Policy!$B$5,Policy!$B$6)),"") -> 0.021896839 | P6: =IF(O6="","",O6*Policy!$B$3*Policy!$B$2) -> 21896.839 | Q6: 0.06997524 | R6: 0.39489842 | S6: 0.97812632
A7: SPY | B7: S&P 500 ETF | C7: US | D7: Broad market | E7: Fund | F7: Accumulate | G7: Up-trend with risk-adjusted momentum >= 0.5. | H7: 778.57 | I7: 770.04 | J7: 778.57 | K7: 723.37951 | L7: =IF(K7="","",K7*(1-Policy!$B$7)) -> 701.67813 | N7: =IF(L7="","",H7/L7-1) -> 0.10958283 | O7: =IF(AND(F7="Accumulate",N7<>"",N7>0),MIN(Policy!$B$4/N7,IF(E7="Stock",Policy!$B$5,Policy!$B$6)),"") -> 0.045627587 | P7: =IF(O7="","",O7*Policy!$B$3*Policy!$B$2) -> 45627.587 | Q7: 0.03128684 | R7: 0.19226057 | S7: 0.92800426
A8: AAPL | B8: Apple | C8: US | D8: Hardware | E8: Stock | F8: Accumulate | G8: Up-trend with risk-adjusted momentum >= 0.5. | H8: 336.64 | I8: 324.808 | J8: 336.64 | K8: 291.2361 | L8: =IF(K8="","",K8*(1-Policy!$B$7)) -> 282.49901 | N8: =IF(L8="","",H8/L8-1) -> 0.19165017 | O8: =IF(AND(F8="Accumulate",N8<>"",N8>0),MIN(Policy!$B$4/N8,IF(E8="Stock",Policy!$B$5,Policy!$B$6)),"") -> 0.026089201 | P8: =IF(O8="","",O8*Policy!$B$3*Policy!$B$2) -> 26089.201 | Q8: 0.067613853 | R8: 0.37252823 | S8: 0.91901946
A9: QQQ | B9: Nasdaq-100 ETF | C9: US | D9: Technology tilt | E9: Fund | F9: Accumulate | G9: Up-trend with risk-adjusted momentum >= 0.5. | H9: 751.27 | I9: 728.461 | J9: 751.27 | K9: 673.02805 | L9: =IF(K9="","",K9*(1-Policy!$B$7)) -> 652.83721 | N9: =IF(L9="","",H9/L9-1) -> 0.15077693 | O9: =IF(AND(F9="Accumulate",N9<>"",N9>0),MIN(Policy!$B$4/N9,IF(E9="Stock",Policy!$B$5,Policy!$B$6)),"") -> 0.033161571 | P9: =IF(O9="","",O9*Policy!$B$3*Policy!$B$2) -> 33161.571 | Q9: 0.035506058 | R9: 0.274419 | S9: 0.84540451
A10: XLV | B10: Health Care Select Sector ETF | C10: US | D10: Healthcare | E10: Fund | F10: Accumulate | G10: Up-trend with risk-adjusted momentum >= 0.5. | H10: 170.81 | I10: 169.172 | J10: 170.81 | K10: 157.15951 | L10: =IF(K10="","",K10*(1-Policy!$B$7)) -> 152.44473 | N10: =IF(L10="","",H10/L10-1) -> 0.12047169 | O10: =IF(AND(F10="Accumulate",N10<>"",N10>0),MIN(Policy!$B$4/N10,IF(E10="Stock",Policy!$B$5,Policy!$B$6)),"") -> 0.041503528 | P10: =IF(O10="","",O10*Policy!$B$3*Policy!$B$2) -> 41503.528 | Q10: 0.061987068 | R10: 0.20195623 | S10: 0.82586939
A11: GOOGL | B11: Alphabet | C11: US | D11: Communication services | E11: Stock | F11: Accumulate | G11: Up-trend with risk-adjusted momentum >= 0.5. | H11: 351.66 | I11: 345.719 | J11: 351.66 | K11: 340.17878 | L11: =IF(K11="","",K11*(1-Policy!$B$7)) -> 329.97342 | N11: =IF(L11="","",H11/L11-1) -> 0.065722212 | O11: =IF(AND(F11="Accumulate",N11<>"",N11>0),MIN(Policy!$B$4/N11,IF(E11="Stock",Policy!$B$5,Policy!$B$6)),"") -> 0.07607778 | P11: =IF(O11="","",O11*Policy!$B$3*Policy!$B$2) -> 76077.78 | Q11: -0.015454393 | R11: 0.48649448 | S11: 0.69745499
A12: NVDA | B12: Nvidia | C12: US | D12: Semiconductors | E12: Stock | F12: Accumulate | G12: Up-trend with risk-adjusted momentum >= 0.5. | H12: 229.28 | I12: 224.061 | J12: 229.28 | K12: 202.04829 | L12: =IF(K12="","",K12*(1-Policy!$B$7)) -> 195.98684 | N12: =IF(L12="","",H12/L12-1) -> 0.16987444 | O12: =IF(AND(F12="Accumulate",N12<>"",N12>0),MIN(Policy!$B$4/N12,IF(E12="Stock",Policy!$B$5,Policy!$B$6)),"") -> 0.029433503 | P12: =IF(O12="","",O12*Policy!$B$3*Policy!$B$2) -> 29433.503 | Q12: 0.086841107 | R12: 0.2518017 | S12: 0.52287637
A13: CRWD | B13: CrowdStrike | C13: US | D13: Software | E13: Stock | F13: Hold | G13: Up-trend but 74% above 40-week average: hold, do not chase; add on pullback. | H13: 275.04 | I13: 229.642 | J13: 275.04 | K13: 157.85476 | L13: =IF(K13="","",K13*(1-Policy!$B$7)) -> 153.11911 | N13: =IF(L13="","",H13/L13-1) -> 0.79624865 | O13: =IF(AND(F13="Accumulate",N13<>"",N13>0),MIN(Policy!$B$4/N13,IF(E13="Stock",Policy!$B$5,Policy!$B$6)),"") | P13: =IF(O13="","",O13*Policy!$B$3*Policy!$B$2) | Q13: 0.46938776 | R13: 1.2700093 | S13: 1.5909439
... A26: ULVR | B26: Unilever | C26: UK | D26: Consumer staples | E26: Stock | F26: Hold | G26: Up-trend but momentum < 0.5 (or market stressed): hold existing, no urgency to add. | H26: 46.77 | I26: 46.4844 | J26: 46.77 | K26: 46.363707 | L26: =IF(K26="","",K26*(1-Policy!$B$7)) -> 44.972796 | N26: =IF(L26="","",H26/L26-1) -> 0.039962023 | O26: =IF(AND(F26="Accumulate",N26<>"",N26>0),MIN(Policy!$B$4/N26,IF(E26="Stock",Policy!$B$5,Policy!$B$6)),"") | P26: =IF(O26="","",O26*Policy!$B$3*Policy!$B$2) | Q26: 0.018155695 | R26: -0.067370685 | S26: -0.11383543
A27: O39 | B27: OCBC | C27: SG | D27: Banks | E27: Stock | F27: Watch | G27: Trend unresolved: wait for price to reclaim both averages. | H27: 29 | L27: =IF(K27="","",K27*(1-Policy!$B$7)) | M27: 31.206 | N27: =IF(L27="","",H27/L27-1) | O27: =IF(AND(F27="Accumulate",N27<>"",N27>0),MIN(Policy!$B$4/N27,IF(E27="Stock",Policy!$B$5,Policy!$B$6)),"") | P27: =IF(O27="","",O27*Policy!$B$3*Policy!$B$2) | Q27: 0.057236602 | R27: 0.71800948 | S27: 1.9259198
A28: D05 | B28: DBS | C28: SG | D28: Banks | E28: Stock | F28: Watch | G28: Trend unresolved: wait for price to reclaim both averages. | H28: 73.36 | L28: =IF(K28="","",K28*(1-Policy!$B$7)) | M28: 76.509 | N28: =IF(L28="","",H28/L28-1) | O28: =IF(AND(F28="Accumulate",N28<>"",N28>0),MIN(Policy!$B$4/N28,IF(E28="Stock",Policy!$B$5,Policy!$B$6)),"") | P28: =IF(O28="","",O28*Policy!$B$3*Policy!$B$2) | Q28: 0.041305891 | R28: 0.36230269 | S28: 1.3236088
A29: ES3 | B29: SPDR Straits Times Index ETF | C29: SG | D29: Broad market | E29: Fund | F29: Watch | G29: Trend unresolved: wait for price to reclaim both averages. | H29: 5.497 | L29: =IF(K29="","",K29*(1-Policy!$B$7)) | M29: 5.7499 | N29: =IF(L29="","",H29/L29-1) | O29: =IF(AND(F29="Accumulate",N29<>"",N29>0),MIN(Policy!$B$4/N29,IF(E29="Stock",Policy!$B$5,Policy!$B$6)),"") | P29: =IF(O29="","",O29*Policy!$B$3*Policy!$B$2) | Q29: -0.013105925 | R29: 0.22564103 | S29: 0.98260889
A30: RIO | B30: Rio Tinto | C30: UK | D30: Materials | E30: Stock | F30: Watch | G30: Trend unresolved: wait for price to reclaim both averages. | H30: 71.16 | L30: =IF(K30="","",K30*(1-Policy!$B$7)) | M30: 73.378 | N30: =IF(L30="","",H30/L30-1) | O30: =IF(AND(F30="Accumulate",N30<>"",N30>0),MIN(Policy!$B$4/N30,IF(E30="Stock",Policy!$B$5,Policy!$B$6)),"") | P30: =IF(O30="","",O30*Policy!$B$3*Policy!$B$2) | Q30: 0.05578635 | R30: 0.42934619 | S30: 0.91722484
A31: HSBA | B31: HSBC | C31: UK | D31: Banks | E31: Stock | F31: Watch | G31: Trend unresolved: wait for price to reclaim both averages. | H31: 13.958 | L31: =IF(K31="","",K31*(1-Policy!$B$7)) | M31: 15.0922 | N31: =IF(L31="","",H31/L31-1) | O31: =IF(AND(F31="Accumulate",N31<>"",N31>0),MIN(Policy!$B$4/N31,IF(E31="Stock",Policy!$B$5,Policy!$B$6)),"") | P31: =IF(O31="","",O31*Policy!$B$3*Policy!$B$2) | Q31: -0.051508562 | R31: 0.40592264 | S31: 0.69208249
A32: 857 | B32: PetroChina H | C32: HK | D32: Energy | E32: Stock | F32: Watch | G32: Trend unresolved: wait for price to reclaim both averages. | H32: 9.83 | L32: =IF(K32="","",K32*(1-Policy!$B$7)) | M32: 9.9013415 | N32: =IF(L32="","",H32/L32-1) | O32: =IF(AND(F32="Accumulate",N32<>"",N32>0),MIN(Policy!$B$4/N32,IF(E32="Stock",Policy!$B$5,Policy!$B$6)),"") | P32: =IF(O32="","",O32*Policy!$B$3*Policy!$B$2) | Q32: 0.088593577 | R32: 0.35213205 | S32: 0.68180897
A33: 5 | B33: HSBC (HK) | C33: HK | D33: Banks | E33: Stock | F33: Watch | G33: Trend unresolved: wait for price to reclaim both averages. | H33: 145.2 | L33: =IF(K33="","",K33*(1-Policy!$B$7)) | M33: 159.02 | N33: =IF(L33="","",H33/L33-1) | O33: =IF(AND(F33="Accumulate",N33<>"",N33>0),MIN(Policy!$B$4/N33,IF(E33="Stock",Policy!$B$5,Policy!$B$6)),"") | P33: =IF(O33="","",O33*Policy!$B$3*Policy!$B$2) | Q33: -0.054071661 | R33: 0.40289855 | S33: 0.67517641
A34: SSE | B34: SSE | C34: UK | D34: Utilities | E34: Stock | F34: Watch | G34: Trend unresolved: wait for price to reclaim both averages. | H34: 24.53 | L34: =IF(K34="","",K34*(1-Policy!$B$7)) | M34: 24.666341 | N34: =IF(L34="","",H34/L34-1) | O34: =IF(AND(F34="Accumulate",N34<>"",N34>0),MIN(Policy!$B$4/N34,IF(E34="Stock",Policy!$B$5,Policy!$B$6)),"") | P34: =IF(O34="","",O34*Policy!$B$3*Policy!$B$2) | Q34: 0.01029654 | R34: 0.34706205 | S34: 0.55243504
A35: 000333 | B35: Midea | C35: China | D35: Industrials | E35: Stock | F35: Watch | G35: Trend unresolved: wait for price to reclaim both averages. | H35: 82.46 | L35: =IF(K35="","",K35*(1-Policy!$B$7)) | M35: 84.05 | N35: =IF(L35="","",H35/L35-1) | O35: =IF(AND(F35="Accumulate",N35<>"",N35>0),MIN(Policy!$B$4/N35,IF(E35="Stock",Policy!$B$5,Policy!$B$6)),"") | P35: =IF(O35="","",O35*Policy!$B$3*Policy!$B$2) | Q35: 0.043929611 | R35: 0.13222573 | S35: 0.52470679
A36: DBA | B36: Invesco DB Agriculture Fund | C36: Cross-asset | D36: Agriculture | E36: Fund | F36: Watch | G36: Trend unresolved: wait for price to reclaim both averages. | H36: 28.33 | L36: =IF(K36="","",K36*(1-Policy!$B$7)) | M36: 28.391 | N36: =IF(L36="","",H36/L36-1) | O36: =IF(AND(F36="Accumulate",N36<>"",N36>0),MIN(Policy!$B$4/N36,IF(E36="Stock",Policy!$B$5,Policy!$B$6)),"") | P36: =IF(O36="","",O36*Policy!$B$3*Policy!$B$2) | Q36: 0.020165646 | R36: 0.076367781 | S36: 0.48004569
A37: ISF | B37: iShares Core FTSE 100 UCITS ETF | C37: UK | D37: Broad market | E37: Fund | F37: Watch | G37: Trend unresolved: wait for price to reclaim both averages. | H37: 10.266 | L37: =IF(K37="","",K37*(1-Policy!$B$7)) | M37: 10.4624 | N37: =IF(L37="","",H37/L37-1) | O37: =IF(AND(F37="Accumulate",N37<>"",N37>0),MIN(Policy!$B$4/N37,IF(E37="Stock",Policy!$B$5,Policy!$B$6)),"") | P37: =IF(O37="","",O37*Policy!$B$3*Policy!$B$2) | Q37: 0.0029308324 | R37: 0.11878814 | S37: 0.47693185
A38: S63 | B38: ST Engineering | C38: SG | D38: Industrials | E38: Stock | F38: Watch | G38: Trend unresolved: wait for price to reclaim both averages. | H38: 10.42 | L38: =IF(K38="","",K38*(1-Policy!$B$7)) | M38: 10.601 | N38: =IF(L38="","",H38/L38-1) | O38: =IF(AND(F38="Accumulate",N38<>"",N38>0),MIN(Policy!$B$4/N38,IF(E38="Stock",Policy!$B$5,Policy!$B$6)),"") | P38: =IF(O38="","",O38*Policy!$B$3*Policy!$B$2) | Q38: -0.049270073 | R38: 0.21871345 | S38: 0.32819057
... A84: A17U | B84: CapitaLand Ascendas REIT | C84: SG | D84: Industrial REIT | E84: Stock | F84: Avoid | G84: Price below 10- and 40-week averages (down-trend): no new money until trend repairs. | H84: 2.19 | L84: =IF(K84="","",K84*(1-Policy!$B$7)) | M84: 2.5414634 | N84: =IF(L84="","",H84/L84-1) | O84: =IF(AND(F84="Accumulate",N84<>"",N84>0),MIN(Policy!$B$4/N84,IF(E84="Stock",Policy!$B$5,Policy!$B$6)),"") | P84: =IF(O84="","",O84*Policy!$B$3*Policy!$B$2) | Q84: -0.13095238 | R84: -0.22887324 | S84: -1.5886457
A86: Totals | N86: Accumulate weight | O86: =SUM(O2:O84) -> 0.40460576 | P86: =SUM(P2:P84) -> 404605.76
A87: Prices in each instrument's quote currency (London in GBP, HK in HKD, China A in CNY, SG in SGD). Amounts are in your base currency: convert before ordering.

Sheet SG Income
A1: Symbol | B1: Name | C1: Price (SGD) | D1: Trailing cash (SGD) | E1: Trailing yield | F1: Fit | G1: Price for 6% | H1: Price for 7% | I1: Price for 8% | J1: Yield if cut 20% | K1: 1y price | L1: Income decision | M1: Plan
A2: ME8U | B2: Mapletree Industrial Trust | C2: 1.83 | D2: 0.1255 | E2: =IF(C2>0,D2/C2,"") -> 0.068579235 | F2: =IF(E2="","no data",IF(E2<Policy!$B$8,"below band",IF(E2>Policy!$B$9,"above band","in band"))) -> in band | G2: =D2/Policy!$B$8 -> 2.0916667 | H2: =D2/((Policy!$B$8+Policy!$B$9)/2) -> 1.7928571 | I2: =D2/Policy!$B$9 -> 1.56875 | J2: =E2*0.8 -> 0.054863388 | K2: -0.14485981 | L2: Accumulate | M2: Yield in target band but price in down-trend: stage in thirds (now, at 1.793 for 7% yield, and after trend repair).
A3: A17U | B3: CapitaLand Ascendas REIT | C3: 2.19 | D3: 0.1501 | E3: =IF(C3>0,D3/C3,"") -> 0.068538813 | F3: =IF(E3="","no data",IF(E3<Policy!$B$8,"below band",IF(E3>Policy!$B$9,"above band","in band"))) -> in band | G3: =D3/Policy!$B$8 -> 2.5016667 | H3: =D3/((Policy!$B$8+Policy!$B$9)/2) -> 2.1442857 | I3: =D3/Policy!$B$9 -> 1.87625 | J3: =E3*0.8 -> 0.05483105 | K3: -0.22887324 | L3: Accumulate | M3: Yield in target band but price in down-trend: stage in thirds (now, at 2.144 for 7% yield, and after trend repair).
A4: M44U | B4: Mapletree Logistics Trust | C4: 1.08 | D4: 0.07266 | E4: =IF(C4>0,D4/C4,"") -> 0.067277778 | F4: =IF(E4="","no data",IF(E4<Policy!$B$8,"below band",IF(E4>Policy!$B$9,"above band","in band"))) -> in band | G4: =D4/Policy!$B$8 -> 1.211 | H4: =D4/((Policy!$B$8+Policy!$B$9)/2) -> 1.038 | I4: =D4/Policy!$B$9 -> 0.90825 | J4: =E4*0.8 -> 0.053822222 | K4: -0.14285714 | L4: Accumulate | M4: Yield in target band but price in down-trend: stage in thirds (now, at 1.038 for 7% yield, and after trend repair).
A5: N2IU | B5: Mapletree Pan Asia Commercial Trust | C5: 1.19 | D5: 0.0792 | E5: =IF(C5>0,D5/C5,"") -> 0.066554622 | F5: =IF(E5="","no data",IF(E5<Policy!$B$8,"below band",IF(E5>Policy!$B$9,"above band","in band"))) -> in band | G5: =D5/Policy!$B$8 -> 1.32 | H5: =D5/((Policy!$B$8+Policy!$B$9)/2) -> 1.1314286 | I5: =D5/Policy!$B$9 -> 0.99 | J5: =E5*0.8 -> 0.053243697 | K5: -0.17931034 | L5: Accumulate | M5: Yield in target band but price in down-trend: stage in thirds (now, at 1.131 for 7% yield, and after trend repair).
A6: AJBU | B6: Keppel DC REIT | C6: 2.13 | D6: 0.13223 | E6: =IF(C6>0,D6/C6,"") -> 0.062079812 | F6: =IF(E6="","no data",IF(E6<Policy!$B$8,"below band",IF(E6>Policy!$B$9,"above band","in band"))) -> in band | G6: =D6/Policy!$B$8 -> 2.2038333 | H6: =D6/((Policy!$B$8+Policy!$B$9)/2) -> 1.889 | I6: =D6/Policy!$B$9 -> 1.652875 | J6: =E6*0.8 -> 0.04966385 | K6: -0.10878661 | L6: Accumulate | M6: Yield in target band but price in down-trend: stage in thirds (now, at 1.889 for 7% yield, and after trend repair).
A7: J69U | B7: Frasers Centrepoint Trust | C7: 2.07 | D7: 0.12099 | E7: =IF(C7>0,D7/C7,"") -> 0.058449275 | F7: =IF(E7="","no data",IF(E7<Policy!$B$8,"below band",IF(E7>Policy!$B$9,"above band","in band"))) -> below band | G7: =D7/Policy!$B$8 -> 2.0165 | H7: =D7/((Policy!$B$8+Policy!$B$9)/2) -> 1.7284286 | I7: =D7/Policy!$B$9 -> 1.512375 | J7: =E7*0.8 -> 0.04675942 | K7: -0.1302521 | L7: Avoid | M7: Yield 5.84% below band; would reach 6% at 2.016.
A8: CJLU | B8: NetLink NBN Trust | C8: 0.955 | D8: 0.0542 | E8: =IF(C8>0,D8/C8,"") -> 0.056753927 | F8: =IF(E8="","no data",IF(E8<Policy!$B$8,"below band",IF(E8>Policy!$B$9,"above band","in band"))) -> below band | G8: =D8/Policy!$B$8 -> 0.90333333 | H8: =D8/((Policy!$B$8+Policy!$B$9)/2) -> 0.77428571 | I8: =D8/Policy!$B$9 -> 0.6775 | J8: =E8*0.8 -> 0.045403141 | K8: -0.0052083333 | L8: Avoid | M8: Yield 5.68% below band; would reach 6% at 0.903.
A9: C38U | B9: CapitaLand Integrated Commercial Trust | C9: 2.24 | D9: 0.1063 | E9: =IF(C9>0,D9/C9,"") -> 0.047455357 | F9: =IF(E9="","no data",IF(E9<Policy!$B$8,"below band",IF(E9>Policy!$B$9,"above band","in band"))) -> below band | G9: =D9/Policy!$B$8 -> 1.7716667 | H9: =D9/((Policy!$B$8+Policy!$B$9)/2) -> 1.5185714 | I9: =D9/Policy!$B$9 -> 1.32875 | J9: =E9*0.8 -> 0.037964286 | K9: -0.042735043 | L9: Avoid | M9: Yield 4.75% below band; would reach 6% at 1.772.
A10: Z74 | B10: Singtel | C10: 4.24 | D10: 0.185 | E10: =IF(C10>0,D10/C10,"") -> 0.043632075 | F10: =IF(E10="","no data",IF(E10<Policy!$B$8,"below band",IF(E10>Policy!$B$9,"above band","in band"))) -> below band | G10: =D10/Policy!$B$8 -> 3.0833333 | H10: =D10/((Policy!$B$8+Policy!$B$9)/2) -> 2.6428571 | I10: =D10/Policy!$B$9 -> 2.3125 | J10: =E10*0.8 -> 0.03490566 | K10: -0.0046948357 | L10: Avoid | M10: Yield 4.36% below band; would reach 6% at 3.083.
A11: D05 | B11: DBS | C11: 73.36 | D11: 3.18 | E11: =IF(C11>0,D11/C11,"") -> 0.043347874 | F11: =IF(E11="","no data",IF(E11<Policy!$B$8,"below band",IF(E11>Policy!$B$9,"above band","in band"))) -> below band | G11: =D11/Policy!$B$8 -> 53 | H11: =D11/((Policy!$B$8+Policy!$B$9)/2) -> 45.428571 | I11: =D11/Policy!$B$9 -> 39.75 | J11: =E11*0.8 -> 0.034678299 | K11: 0.36230269 | L11: Hold | M11: Yield 4.33% below band; would reach 6% at 53.000.
A12: C2PU | B12: Parkway Life REIT | C12: 3.98 | D12: 0.1641 | E12: =IF(C12>0,D12/C12,"") -> 0.041231156 | F12: =IF(E12="","no data",IF(E12<Policy!$B$8,"below band",IF(E12>Policy!$B$9,"above band","in band"))) -> below band | G12: =D12/Policy!$B$8 -> 2.735 | H12: =D12/((Policy!$B$8+Policy!$B$9)/2) -> 2.3442857 | I12: =D12/Policy!$B$9 -> 2.05125 | J12: =E12*0.8 -> 0.032984925 | K12: -0.038647343 | L12: Hold | M12: Yield 4.12% below band; would reach 6% at 2.735.
A13: U11 | B13: UOB | C13: 39.96 | D13: 1.59 | E13: =IF(C13>0,D13/C13,"") -> 0.03978979 | F13: =IF(E13="","no data",IF(E13<Policy!$B$8,"below band",IF(E13>Policy!$B$9,"above band","in band"))) -> below band | G13: =D13/Policy!$B$8 -> 26.5 | H13: =D13/((Policy!$B$8+Policy!$B$9)/2) -> 22.714286 | I13: =D13/Policy!$B$9 -> 19.875 | J13: =E13*0.8 -> 0.031831832 | K13: 0.1310501 | L13: Hold | M13: Yield 3.98% below band; would reach 6% at 26.500.
... A15: S63 | B15: ST Engineering | C15: 10.42 | D15: 0.24 | E15: =IF(C15>0,D15/C15,"") -> 0.02303263 | F15: =IF(E15="","no data",IF(E15<Policy!$B$8,"below band",IF(E15>Policy!$B$9,"above band","in band"))) -> below band | G15: =D15/Policy!$B$8 -> 4 | H15: =D15/((Policy!$B$8+Policy!$B$9)/2) -> 3.4285714 | I15: =D15/Policy!$B$9 -> 3 | J15: =E15*0.8 -> 0.018426104 | K15: 0.21871345 | L15: Hold | M15: Yield 2.30% below band; would reach 6% at 4.000.
A17: Trailing cash = distributions with ex-date in the 365 days to the as-of date, from IBKR corporate actions, cross-checked to IBKR dividend yield.

Sheet FX
A1: Pair | B1: Trend | C1: Read | D1: 3m change
A2: GBP/USD | B2: mixed | C2: No clear trend | D2: -0.012752867
A3: EUR/USD | B3: down | C3: EUR weakening vs USD | D3: -0.018878255
A4: EUR/GBP | B4: down | C4: EUR weakening vs GBP | D4: -0.0066032752
A5: USD/JPY | B5: mixed | C5: No clear trend | D5: -0.020888415
A6: USD/SGD | B6: mixed | C6: No clear trend | D6: -0.0084967194
A7: USD/HKD | B7: up | C7: USD strengthening vs HKD | D7: 0.0010778955
A8: USD/CNH | B8: down | C8: USD weakening vs CNH | D8: -0.013126417
A9: AUD/USD | B9: mixed | C9: No clear trend | D9: 0.0037731781
A10: USD/CHF | B10: up | C10: USD strengthening vs CHF | D10: 0.026809734

Sheet Options
A1: Underlying | B1: Structure | C1: Legs | D1: Expiry | E1: Days | F1: Spot | G1: Debit / share | H1: Cost per contract | I1: Breakeven | J1: Move to breakeven | K1: Max gain / share | L1: Reward : risk | M1: Prob. of profit | N1: IV | O1: Contracts (per-trade budget) | P1: Premium at risk | Q1: Stop: close at value
A2: XOM | B2: Bull call spread | C2: Buy 170C / Sell 185C | D2: 2026-12-18 | E2: 70 | F2: 168.79 | G2: 4.87 | H2: =G2*100 -> 487 | I2: 174.87 | J2: =I2/F2-1 -> 0.036021091 | K2: 10.13 | L2: =IF(K2="","open",K2/G2) -> 2.0800821 | M2: 0.38715849 | N2: 0.28104455 | O2: =INT(Policy!$B$2*Policy!$B$11/H2) -> 20 | P2: =O2*H2 -> 9740 | Q2: =G2*(1-0.5) -> 2.435
A3: GLD | B3: Bear put spread | C3: Buy 385P / Sell 345P | D3: 2026-12-18 | E3: 70 | F3: 384.5 | G3: 10.935 | H3: =G3*100 -> 1093.5 | I3: 374.065 | J3: =I3/F3-1 -> -0.027139142 | K3: 29.065 | L3: =IF(K3="","open",K3/G3) -> 2.657979 | M3: 0.36962836 | N3: 0.21186506 | O3: =INT(Policy!$B$2*Policy!$B$11/H3) -> 9 | P3: =O3*H3 -> 9841.5 | Q3: =G3*(1-0.5) -> 5.4675
A4: GOOGL | B4: Bull call spread | C4: Buy 350C / Sell 385C | D4: 2026-12-18 | E4: 70 | F4: 351.6 | G4: 13.15 | H4: =G4*100 -> 1315 | I4: 363.15 | J4: =I4/F4-1 -> 0.032849829 | K4: 21.85 | L4: =IF(K4="","open",K4/G4) -> 1.661597 | M4: 0.40371617 | N4: 0.32699793 | O4: =INT(Policy!$B$2*Policy!$B$11/H4) -> 7 | P4: =O4*H4 -> 9205 | Q4: =G4*(1-0.5) -> 6.575
A5: AAPL | B5: Bull call spread | C5: Buy 335C / Sell 370C | D5: 2026-12-18 | E5: 70 | F5: 336.08 | G5: 12.65 | H5: =G5*100 -> 1265 | I5: 347.65 | J5: =I5/F5-1 -> 0.034426327 | K5: 22.35 | L5: =IF(K5="","open",K5/G5) -> 1.7667984 | M5: 0.38331307 | N5: 0.24606412 | O5: =INT(Policy!$B$2*Policy!$B$11/H5) -> 7 | P5: =O5*H5 -> 8855 | Q5: =G5*(1-0.5) -> 6.325
A6: ORCL | B6: Bear put spread | C6: Buy 140P / Sell 125P | D6: 2026-12-18 | E6: 70 | F6: 141.55 | G6: 6.55 | H6: =G6*100 -> 655 | I6: 133.45 | J6: =I6/F6-1 -> -0.057223596 | K6: 8.45 | L6: =IF(K6="","open",K6/G6) -> 1.2900763 | M6: 0.44312252 | N6: 0.56844486 | O6: =INT(Policy!$B$2*Policy!$B$11/H6) -> 15 | P6: =O6*H6 -> 9825 | Q6: =G6*(1-0.5) -> 3.275
A7: NVDA | B7: Bull call spread | C7: Buy 230C / Sell 250C | D7: 2026-12-18 | E7: 70 | F7: 229.33 | G7: 7.825 | H7: =G7*100 -> 782.5 | I7: 237.825 | J7: =I7/F7-1 -> 0.03704269 | K7: 12.175 | L7: =IF(K7="","open",K7/G7) -> 1.5559105 | M7: 0.39477977 | N7: 0.34095347 | O7: =INT(Policy!$B$2*Policy!$B$11/H7) -> 12 | P7: =O7*H7 -> 9390 | Q7: =G7*(1-0.5) -> 3.9125
A8: QQQ | B8: Bull call spread | C8: Buy 751C / Sell 825C | D8: 2026-12-18 | E8: 70 | F8: 751.38 | G8: 25.26 | H8: =G8*100 -> 2526 | I8: 776.26 | J8: =I8/F8-1 -> 0.033112407 | K8: 48.74 | L8: =IF(K8="","open",K8/G8) -> 1.9295329 | M8: 0.36896274 | N8: 0.19479263 | O8: =INT(Policy!$B$2*Policy!$B$11/H8) -> 3 | P8: =O8*H8 -> 7578 | Q8: =G8*(1-0.5) -> 12.63
A9: SPY | B9: Bull call spread | C9: Buy 779C / Sell 855C | D9: 2026-12-18 | E9: 70 | F9: 778.57 | G9: 20.395 | H9: =G9*100 -> 2039.5 | I9: 799.395 | J9: =I9/F9-1 -> 0.026747756 | K9: 55.605 | L9: =IF(K9="","open",K9/G9) -> 2.7264035 | M9: 0.36347279 | N9: 0.13365026 | O9: =INT(Policy!$B$2*Policy!$B$11/H9) -> 4 | P9: =O9*H9 -> 8158 | Q9: =G9*(1-0.5) -> 10.1975
A10: ORCL | B10: Long put | C10: Buy 135P | D10: 2026-12-18 | E10: 70 | F10: 141.55 | G10: 10.15 | H10: =G10*100 -> 1015 | I10: 124.85 | J10: =I10/F10-1 -> -0.11797951 | L10: =IF(K10="","open",K10/G10) -> open | M10: 0.33988123 | N10: 0.56660729 | O10: =INT(Policy!$B$2*Policy!$B$11/H10) -> 9 | P10: =O10*H10 -> 9135 | Q10: =G10*(1-0.5) -> 5.075
A11: XOM | B11: Long call | C11: Buy 175C | D11: 2026-12-18 | E11: 70 | F11: 168.79 | G11: 5.65 | H11: =G11*100 -> 565 | I11: 180.65 | J11: =I11/F11-1 -> 0.070264826 | L11: =IF(K11="","open",K11/G11) -> open | M11: 0.28931761 | N11: 0.27816646 | O11: =INT(Policy!$B$2*Policy!$B$11/H11) -> 17 | P11: =O11*H11 -> 9605 | Q11: =G11*(1-0.5) -> 2.825
A12: NVDA | B12: Long call | C12: Buy 240C | D12: 2026-12-18 | E12: 70 | F12: 229.33 | G12: 9.725 | H12: =G12*100 -> 972.5 | I12: 249.725 | J12: =I12/F12-1 -> 0.088932979 | L12: =IF(K12="","open",K12/G12) -> open | M12: 0.27376274 | N12: 0.33524543 | O12: =INT(Policy!$B$2*Policy!$B$11/H12) -> 10 | P12: =O12*H12 -> 9725 | Q12: =G12*(1-0.5) -> 4.8625
A13: GOOGL | B13: Long call | C13: Buy 370C | D13: 2026-12-18 | E13: 70 | F13: 351.6 | G13: 13.675 | H13: =G13*100 -> 1367.5 | I13: 383.675 | J13: =I13/F13-1 -> 0.091225825 | L13: =IF(K13="","open",K13/G13) -> open | M13: 0.26387139 | N13: 0.32446786 | O13: =INT(Policy!$B$2*Policy!$B$11/H13) -> 7 | P13: =O13*H13 -> 9572.5 | Q13: =G13*(1-0.5) -> 6.8375
A14: GLD | B14: Long put | C14: Buy 365P | D14: 2026-12-18 | E14: 70 | F14: 384.5 | G14: 5.525 | H14: =G14*100 -> 552.5 | I14: 359.475 | J14: =I14/F14-1 -> -0.065084525 | L14: =IF(K14="","open",K14/G14) -> open | M14: 0.22652458 | N14: 0.21470213 | O14: =INT(Policy!$B$2*Policy!$B$11/H14) -> 18 | P14: =O14*H14 -> 9945 | Q14: =G14*(1-0.5) -> 2.7625
A15: AAPL | B15: Long call | C15: Buy 355C | D15: 2026-12-18 | E15: 70 | F15: 336.08 | G15: 7.75 | H15: =G15*100 -> 775 | I15: 362.75 | J15: =I15/F15-1 -> 0.079356106 | L15: =IF(K15="","open",K15/G15) -> open | M15: 0.23703063 | N15: 0.23617352 | O15: =INT(Policy!$B$2*Policy!$B$11/H15) -> 12 | P15: =O15*H15 -> 9300 | Q15: =G15*(1-0.5) -> 3.875
A16: QQQ | B16: Long call | C16: Buy 789C | D16: 2026-12-18 | E16: 70 | F16: 751.38 | G16: 11.02 | H16: =G16*100 -> 1102 | I16: 800.02 | J16: =I16/F16-1 -> 0.064734222 | L16: =IF(K16="","open",K16/G16) -> open | M16: 0.22431632 | N16: 0.17474099 | O16: =INT(Policy!$B$2*Policy!$B$11/H16) -> 9 | P16: =O16*H16 -> 9918 | Q16: =G16*(1-0.5) -> 5.51
A17: SPY | B17: Long call | C17: Buy 817C | D17: 2026-12-18 | E17: 70 | F17: 778.57 | G17: 4.66 | H17: =G17*100 -> 466 | I17: 821.66 | J17: =I17/F17-1 -> 0.055345056 | L17: =IF(K17="","open",K17/G17) -> open | M17: 0.17179132 | N17: 0.11440579 | O17: =INT(Policy!$B$2*Policy!$B$11/H17) -> 21 | P17: =O17*H17 -> 9786 | Q17: =G17*(1-0.5) -> 2.33
A19: Sleeve check | O19: Total if all taken | P19: =SUM(P2:P17) -> 149579
O20: Sleeve cap | P20: =Policy!$B$2*Policy!$B$10 -> 50000
O21: Within cap? | P21: =IF(P19<=P20,"Yes","No: pick fewer trades") -> No: pick fewer trades
A23: Probability of profit is risk-neutral, from the option's implied volatility. Debits are mid prices from IBKR weekend quotes; re-price live before trading. Defined risk only: maximum loss = premium paid.

Sheet Decision Log
A1: Date | B1: Symbol | C1: Decision | D1: Price | E1: Weight | F1: Exit level | G1: Assumption (must be true) | H1: Strongest counter-case | I1: Pre-mortem: top reason it fails | J1: Review date | K1: Outcome (fill at review)
A2: 2026-10-12 | B2: XLE | C2: Accumulate | D2: 65.08 | E2: 0.029 | F2: 55.59 | G2: Oil stays in up-trend through Q1 2027 | H2: OPEC supply increase reverses oil | I2: Demand slowdown cuts oil 20% | J2: 2026-12-12
